{
  "patch_id": "91587af0-73fe-42f1-8c8f-5b84a54fd1dc",
  "timestamp": "2025-11-24T16:26:25.762635",
  "author": "Blastbrean",
  "diff": {
    "animation": {
      "rbxassetid://6466993564": {
        "status": "modified",
        "changes": {
          "hitbox": {
            "from": {
              "Y": 24.200000762939453,
              "X": 24.200000762939453,
              "Z": 24.200000762939453
            },
            "to": {
              "Y": 16.000001907348633,
              "X": 16.000001907348633,
              "Z": 16.000001907348633
            }
          }
        }
      }
    }
  }
}